brazil_fiscal_client/__init__.py
brazil_fiscal_client/fiscal_client.py
brazil_fiscal_client-0.1.0.dist-info/licenses/LICENSE
brazil_fiscal_client-0.1.0.dist-info/METADATA
brazil_fiscal_client-0.1.0.dist-info/WHEEL
brazil_fiscal_client-0.1.0.dist-info/entry_points.txt
brazil_fiscal_client-0.1.0.dist-info/top_level.txt
brazil_fiscal_client-0.1.0.dist-info/RECORD
