Metadata-Version: 2.4
Name: brazil-fiscal-client
Version: 0.1.0
Summary: SOAP client for the Brazilian Fiscal Authorities
Author-email: Raphael Valyi <raphael.valyi@akretion.com>
License: MIT
Project-URL: Homepage, https://github.com/akretion/brazil-fiscal-client
Project-URL: Source, https://github.com/akretion/brazil-fiscal-client
Project-URL: Documentation, https://github.com/akretion/brazil-fiscal-client
Keywords: soap,wsdl,nfe,fazenda,binding,nfelib,odoo
Classifier: Intended Audience :: Developers
Classifier: License :: OSI Approved :: MIT License
Classifier: Operating System :: OS Independent
Classifier: Programming Language :: Python
Classifier: Programming Language :: Python :: 3
Classifier: Programming Language :: Python :: 3 :: Only
Classifier: Programming Language :: Python :: 3.8
Classifier: Programming Language :: Python :: 3.9
Classifier: Programming Language :: Python :: 3.10
Classifier: Programming Language :: Python :: 3.11
Classifier: Programming Language :: Python :: 3.12
Classifier: Programming Language :: Python :: Implementation :: CPython
Classifier: Programming Language :: Python :: Implementation :: PyPy
Classifier: Topic :: Software Development
Requires-Python: >=3.8
License-File: LICENSE
Requires-Dist: xsdata
Requires-Dist: requests
Requires-Dist: requests-pkcs12
Provides-Extra: test
Requires-Dist: pre-commit; extra == "test"
Requires-Dist: pytest; extra == "test"
Requires-Dist: pytest-cov; extra == "test"
Dynamic: license-file
